{"mean":{"confidence_interval":{"confidence_level":0.95,"lower_bound":713.8066551947682,"upper_bound":720.2019800179448},"point_estimate":717.0553358607048,"standard_error":1.6261574214998167},"median":{"confidence_interval":{"confidence_level":0.95,"lower_bound":715.1139658140751,"upper_bound":724.7107555589951},"point_estimate":719.9177367233706,"standard_error":2.68314262071388},"median_abs_dev":{"confidence_interval":{"confidence_level":0.95,"lower_bound":11.132892739622006,"upper_bound":19.23644901272341},"point_estimate":13.606048527966262,"standard_error":2.1953248641582976},"slope":{"confidence_interval":{"confidence_level":0.95,"lower_bound":716.4045450291957,"upper_bound":725.0461241867167},"point_estimate":720.7689099752944,"standard_error":2.2119987067608524},"std_dev":{"confidence_interval":{"confidence_level":0.95,"lower_bound":13.831115388421592,"upper_bound":18.49400031058745},"point_estimate":16.325083739958067,"standard_error":1.189832404284929}}