{"mean":{"confidence_interval":{"confidence_level":0.95,"lower_bound":658.9829829934996,"upper_bound":677.5207902526846},"point_estimate":669.0091554736729,"standard_error":4.761628250082888},"median":{"confidence_interval":{"confidence_level":0.95,"lower_bound":681.6798303737079,"upper_bound":686.3452052635727},"point_estimate":683.4789322700117,"standard_error":1.0861040862711786},"median_abs_dev":{"confidence_interval":{"confidence_level":0.95,"lower_bound":6.923213316396121,"upper_bound":11.761470249780707},"point_estimate":9.546563984639647,"standard_error":1.2513090461520031},"slope":{"confidence_interval":{"confidence_level":0.95,"lower_bound":684.0478637785881,"upper_bound":686.4793579153821},"point_estimate":685.2828195052219,"standard_error":0.6224264136683851},"std_dev":{"confidence_interval":{"confidence_level":0.95,"lower_bound":29.600982877193534,"upper_bound":62.56701325869295},"point_estimate":47.80442503908972,"standard_error":8.410025194766273}}