{"mean":{"confidence_interval":{"confidence_level":0.95,"lower_bound":610.7179256951306,"upper_bound":626.0028320274756},"point_estimate":617.8593785514623,"standard_error":3.903213394926314},"median":{"confidence_interval":{"confidence_level":0.95,"lower_bound":601.354558023781,"upper_bound":609.877220930917},"point_estimate":605.0479461880711,"standard_error":2.0379386127740844},"median_abs_dev":{"confidence_interval":{"confidence_level":0.95,"lower_bound":11.663231722146252,"upper_bound":20.852675806143818},"point_estimate":15.495014985589867,"standard_error":2.350261179169724},"slope":{"confidence_interval":{"confidence_level":0.95,"lower_bound":605.259683801446,"upper_bound":622.3299897280538},"point_estimate":612.8611335478112,"standard_error":4.380845992918388},"std_dev":{"confidence_interval":{"confidence_level":0.95,"lower_bound":25.411007267822388,"upper_bound":51.428841309493976},"point_estimate":39.35193037920075,"standard_error":6.624206852175226}}