{"mean":{"confidence_interval":{"confidence_level":0.95,"lower_bound":531.1030888593951,"upper_bound":632.104549166825},"point_estimate":567.193283058944,"standard_error":30.090826516578435},"median":{"confidence_interval":{"confidence_level":0.95,"lower_bound":520.8545893988909,"upper_bound":541.8772875816993},"point_estimate":530.1960975277646,"standard_error":5.732389176889921},"median_abs_dev":{"confidence_interval":{"confidence_level":0.95,"lower_bound":30.97651550908472,"upper_bound":51.23860246254394},"point_estimate":42.419766677210255,"standard_error":5.04953814856164},"slope":{"confidence_interval":{"confidence_level":0.95,"lower_bound":515.0184460496316,"upper_bound":536.1453507875248},"point_estimate":524.7585471352228,"standard_error":5.4067474854021675},"std_dev":{"confidence_interval":{"confidence_level":0.95,"lower_bound":35.47760414965815,"upper_bound":517.3867621912983},"point_estimate":303.2113771788271,"standard_error":171.38004268123112}}