{"mean":{"confidence_interval":{"confidence_level":0.95,"lower_bound":4396.602426745186,"upper_bound":5311.638803686196},"point_estimate":4746.0861484502275,"standard_error":243.77496027419875},"median":{"confidence_interval":{"confidence_level":0.95,"lower_bound":4289.852182539683,"upper_bound":4619.872294372294},"point_estimate":4451.997448979591,"standard_error":98.8914559386342},"median_abs_dev":{"confidence_interval":{"confidence_level":0.95,"lower_bound":382.0891543276727,"upper_bound":699.8606395908637},"point_estimate":527.7812705718696,"standard_error":74.56489443639482},"slope":{"confidence_interval":{"confidence_level":0.95,"lower_bound":4195.825475410977,"upper_bound":4824.509953065245},"point_estimate":4491.6885125996605,"standard_error":161.1666593684093},"std_dev":{"confidence_interval":{"confidence_level":0.95,"lower_bound":587.5775169767093,"upper_bound":4042.661250754521},"point_estimate":2439.543604233532,"standard_error":1129.9446664270283}}