{"mean":{"confidence_interval":{"confidence_level":0.95,"lower_bound":542.6951338566196,"upper_bound":565.7861091942175},"point_estimate":554.725785118769,"standard_error":5.907036472459135},"median":{"confidence_interval":{"confidence_level":0.95,"lower_bound":567.1299652777777,"upper_bound":582.9429659498207},"point_estimate":576.801934754522,"standard_error":4.255539786874876},"median_abs_dev":{"confidence_interval":{"confidence_level":0.95,"lower_bound":19.73581518195756,"upper_bound":34.7644698262772},"point_estimate":26.92576380753681,"standard_error":3.8006449363179255},"slope":{"confidence_interval":{"confidence_level":0.95,"lower_bound":576.9283493065956,"upper_bound":585.316547194699},"point_estimate":581.1624316536131,"standard_error":2.1331154790682287},"std_dev":{"confidence_interval":{"confidence_level":0.95,"lower_bound":45.86933612326014,"upper_bound":70.28565713529848},"point_estimate":59.336367762200005,"standard_error":6.216496519640016}}