{"mean":{"confidence_interval":{"confidence_level":0.95,"lower_bound":6206760.348027779,"upper_bound":6340567.97088889},"point_estimate":6271166.898888889,"standard_error":34089.27093423724},"median":{"confidence_interval":{"confidence_level":0.95,"lower_bound":6120217.222222222,"upper_bound":6281024.444444444},"point_estimate":6241668.444444444,"standard_error":43860.09297854243},"median_abs_dev":{"confidence_interval":{"confidence_level":0.95,"lower_bound":226041.22795363236,"upper_bound":355901.9125481439},"point_estimate":323556.19365572906,"standard_error":36889.371630096146},"slope":null,"std_dev":{"confidence_interval":{"confidence_level":0.95,"lower_bound":258545.8916873243,"upper_bound":415926.0733733231},"point_estimate":342257.31527365773,"standard_error":40165.52045944572}}